logger_color/__init__.py
logger_color/cformatter.py
logger_color/clogger.py
logger_color/functions.py
logger_color/py.typed
logger_color-0.2.0.dist-info/LICENSE.txt
logger_color-0.2.0.dist-info/METADATA
logger_color-0.2.0.dist-info/WHEEL
logger_color-0.2.0.dist-info/RECORD
