Metadata-Version: 2.1
Name: logger_color
Version: 0.2.0
Summary: Color the log message headers and add more logging levels for diagnostics.
Home-page: https://github.com/vladimirs-git/logger-color
License: Apache-2.0
Keywords: logging,logger,color
Author: Vladimirs Prusakovs
Author-email: vladimir.prusakovs@gmail.com
Requires-Python: >=3.8,<4.0
Classifier: Development Status :: 5 - Production/Stable
Classifier: Intended Audience :: Developers
Classifier: License :: OSI Approved :: Apache Software License
Classifier: Natural Language :: English
Classifier: Programming Language :: Python :: 3
Classifier: Programming Language :: Python :: 3.8
Classifier: Programming Language :: Python :: 3.9
Classifier: Programming Language :: Python :: 3.10
Classifier: Programming Language :: Python :: 3.11
Classifier: Programming Language :: Python :: 3.12
Classifier: Programming Language :: Python :: 3.13
Provides-Extra: test
Project-URL: Bug Tracker, https://github.com/vladimirs-git/logger-color/issues
Project-URL: Download URL, https://github.com/vladimirs-git/logger-color/archive/refs/tags/0.2.0.tar.gz
Project-URL: Repository, https://github.com/vladimirs-git/logger-color
